README.rst
setup.py
tutor_lts.egg-info/PKG-INFO
tutor_lts.egg-info/SOURCES.txt
tutor_lts.egg-info/dependency_links.txt
tutor_lts.egg-info/entry_points.txt
tutor_lts.egg-info/requires.txt
tutor_lts.egg-info/top_level.txt
tutorlts/__about__.py
tutorlts/__init__.py
tutorlts/lts.c
tutorlts/plugin.py