Metadata-Version: 2.1
Name: tutor-lts
Version: 9.1.6
Summary: Tutor LTS management plugin
Home-page: https://overhang.io/tutor/lts
Author: Overhang.IO
License: UNKNOWN
Project-URL: Homepage, https://overhang.io/tutor/lts
Platform: UNKNOWN
Classifier: Development Status :: 5 - Production/Stable
Classifier: Intended Audience :: Developers
Classifier: License :: Other/Proprietary License
Classifier: Operating System :: OS Independent
Classifier: Programming Language :: Python
Classifier: Programming Language :: Python :: 3.5
Classifier: Programming Language :: Python :: 3.6
Classifier: Programming Language :: Python :: 3.7
Requires-Python: >=3.5
